agentsudo/__init__.py
agentsudo/core.py
agentsudo/guard.py
agentsudo/integrations.py
agentsudo/adapters/__init__.py
agentsudo/adapters/fastapi.py
agentsudo-0.2.0.dist-info/licenses/LICENSE
agentsudo-0.2.0.dist-info/METADATA
agentsudo-0.2.0.dist-info/WHEEL
agentsudo-0.2.0.dist-info/top_level.txt
agentsudo-0.2.0.dist-info/RECORD
