Metadata-Version: 2.4
Name: agentsudo
Version: 0.2.0
Summary: The permission layer for AI agents. Enforce scopes, approvals, and safe tool use across LangChain, LlamaIndex, FastAPI, and custom agents.
Author: xywa23
License: MIT License
Project-URL: Homepage, https://github.com/xywa23/agentsudo
Project-URL: Documentation, https://agentsudo.vercel.app/docs
Project-URL: Repository, https://github.com/xywa23/agentsudo
Project-URL: Bug Tracker, https://github.com/xywa23/agentsudo/issues
Keywords: ai,agents,permissions,security,langchain,llamaindex,fastapi,llm,iam,authorization
Classifier: Development Status :: 4 - Beta
Classifier: Intended Audience :: Developers
Classifier: Topic :: Security
Classifier: Topic :: Software Development :: Libraries :: Python Modules
Classifier: Programming Language :: Python :: 3
Classifier: Programming Language :: Python :: 3.9
Classifier: Programming Language :: Python :: 3.10
Classifier: Programming Language :: Python :: 3.11
Classifier: Programming Language :: Python :: 3.12
Classifier: License :: OSI Approved :: MIT License
Classifier: Operating System :: OS Independent
Requires-Python: >=3.9
License-File: LICENSE
Provides-Extra: fastapi
Requires-Dist: fastapi>=0.100.0; extra == "fastapi"
Requires-Dist: starlette>=0.27.0; extra == "fastapi"
Provides-Extra: pydantic
Requires-Dist: pydantic>=2.0.0; extra == "pydantic"
Provides-Extra: test
Requires-Dist: pytest; extra == "test"
Requires-Dist: pydantic>=2.0.0; extra == "test"
Provides-Extra: all
Requires-Dist: fastapi>=0.100.0; extra == "all"
Requires-Dist: starlette>=0.27.0; extra == "all"
Requires-Dist: pydantic>=2.0.0; extra == "all"
Dynamic: license-file
